CHANGES
LICENSE
MANIFEST.in
README.rst
setup.cfg
setup.py
tox.ini
futurify/__init__.py
futurify.egg-info/PKG-INFO
futurify.egg-info/SOURCES.txt
futurify.egg-info/dependency_links.txt
futurify.egg-info/entry_points.txt
futurify.egg-info/not-zip-safe
futurify.egg-info/top_level.txt
futurify/tests/__init__.py
futurify/tests/test_full.py
futurify/tests/test_units.py