Metadata-Version: 1.1
Name: futurify
Version: 0.1
Summary: Manage __future__ imports.
Home-page: http://github.com/storborg/futurify
Author: Scott Torborg
Author-email: scott@cartlogic.com
License: MIT
Keywords: future imports syntax static analysis lint
Platform: UNKNOWN
Classifier: Development Status :: 2 - Pre-Alpha
Classifier: License :: OSI Approved :: MIT License
Classifier: Programming Language :: Python :: 2
Classifier: Programming Language :: Python :: 2.7
